Products.ZPsycopgDA-4.3-py3.13-nspkg.pth
Products/ZPsycopgDA/DA.py
Products/ZPsycopgDA/__init__.py
Products/ZPsycopgDA/db.py
Products/ZPsycopgDA/permissions.py
Products/ZPsycopgDA/pool.py
Products/ZPsycopgDA/utils.py
Products/ZPsycopgDA/dtml/add.dtml
Products/ZPsycopgDA/dtml/browse.dtml
Products/ZPsycopgDA/dtml/edit.dtml
Products/ZPsycopgDA/dtml/table_info.dtml
Products/ZPsycopgDA/icons/DBAdapterFolder_icon.gif
Products/ZPsycopgDA/icons/bin.svg
Products/ZPsycopgDA/icons/da.svg
Products/ZPsycopgDA/icons/date.svg
Products/ZPsycopgDA/icons/datetime.svg
Products/ZPsycopgDA/icons/db_view.svg
Products/ZPsycopgDA/icons/field.svg
Products/ZPsycopgDA/icons/float.svg
Products/ZPsycopgDA/icons/int.svg
Products/ZPsycopgDA/icons/stable.svg
Products/ZPsycopgDA/icons/table.svg
Products/ZPsycopgDA/icons/text.svg
Products/ZPsycopgDA/icons/time.svg
Products/ZPsycopgDA/icons/what.svg
Products/ZPsycopgDA/tests/__init__.py
Products/ZPsycopgDA/tests/dummy.py
Products/ZPsycopgDA/tests/test_DA.py
Products/ZPsycopgDA/tests/test_db.py
Products/ZPsycopgDA/tests/test_utils.py
Products/ZPsycopgDA/tests/utils.py
products_zpsycopgda-4.3.dist-info/licenses/LICENSE.txt
products_zpsycopgda-4.3.dist-info/licenses/LICENSE_OLD.txt
products_zpsycopgda-4.3.dist-info/METADATA
products_zpsycopgda-4.3.dist-info/WHEEL
products_zpsycopgda-4.3.dist-info/namespace_packages.txt
products_zpsycopgda-4.3.dist-info/top_level.txt
products_zpsycopgda-4.3.dist-info/RECORD
