Metadata-Version: 2.4
Name: Products.ZPsycopgDA
Version: 4.3
Summary: Zope database adapter for PostGreSQL
Home-page: https://github.com/dataflake/Products.ZPsycopgDA
Author: Federico Di Gregorio
Author-email: fog@initd.org
Maintainer: Jens Vagelpohl
Maintainer-email: jens@dataflake.org
License: ZPL-2.1
Project-URL: Documentation, https://zpsycopgda.readthedocs.io
Project-URL: Issue Tracker, https://github.com/dataflake/Products.ZPsycopgDA/issues
Project-URL: Sources, https://github.com/dataflake/Products.ZPsycopgDA
Classifier: Development Status :: 5 - Production/Stable
Classifier: Environment :: Web Environment
Classifier: Framework :: Zope
Classifier: Framework :: Zope :: 5
Classifier: License :: OSI Approved :: Zope Public License
Classifier: Operating System :: OS Independent
Classifier: Programming Language :: Python
Classifier: Programming Language :: Python :: 3
Classifier: Programming Language :: Python :: 3.9
Classifier: Programming Language :: Python :: 3.10
Classifier: Programming Language :: Python :: 3.11
Classifier: Programming Language :: Python :: 3.12
Classifier: Programming Language :: Python :: 3.13
Classifier: Programming Language :: Python :: Implementation :: CPython
Classifier: Topic :: Database
Classifier: Topic :: Database :: Front-Ends
Requires-Python: >=3.9
License-File: LICENSE.txt
License-File: LICENSE_OLD.txt
Requires-Dist: setuptools
Requires-Dist: psycopg2>=2.4.2
Requires-Dist: Zope>=5
Requires-Dist: Products.ZSQLMethods
Provides-Extra: docs
Requires-Dist: Sphinx; extra == "docs"
Requires-Dist: furo; extra == "docs"
Requires-Dist: pkginfo; extra == "docs"
Dynamic: author
Dynamic: author-email
Dynamic: classifier
Dynamic: description
Dynamic: description-content-type
Dynamic: home-page
Dynamic: license
Dynamic: license-file
Dynamic: maintainer
Dynamic: maintainer-email
Dynamic: project-url
Dynamic: provides-extra
Dynamic: requires-dist
Dynamic: requires-python
Dynamic: summary
